webspace/__init__.py
webspace/api.py
webspace/base_settings.py
webspace/formatter.py
webspace/loader.py
webspace/loading.py
webspace/middleware.py
webspace/urls.py
webspace/views.py
webspace/account/__init__.py
webspace/account/admin.py
webspace/account/apps.py
webspace/account/models.py
webspace/account/utils.py
webspace/account/management/__init__.py
webspace/account/management/commands/__init__.py
webspace/account/management/commands/account.py
webspace/account/migrations/0001_initial.py
webspace/account/migrations/0002_auto_20200702_1608.py
webspace/account/migrations/0003_auto_20200702_1747.py
webspace/account/migrations/0004_auto_20200702_1758.py
webspace/account/migrations/0005_auto_20200702_1830.py
webspace/account/migrations/0006_auto_20200702_2018.py
webspace/account/migrations/__init__.py
webspace/bakery/__init__.py
webspace/bakery/abstract.py
webspace/bakery/admin.py
webspace/bakery/apps.py
webspace/bakery/celery.py
webspace/bakery/celeryconfig.py
webspace/bakery/models.py
webspace/bakery/signal_handlers.py
webspace/bakery/urls.py
webspace/bakery/views_admin.py
webspace/bakery/wagtail_hooks.py
webspace/bakery/management/__init__.py
webspace/bakery/management/commands/__init__.py
webspace/bakery/management/commands/build.py
webspace/bakery/migrations/0001_initial.py
webspace/bakery/migrations/0002_versionbuild.py
webspace/bakery/migrations/__init__.py
webspace/bakery/views/__init__.py
webspace/bakery/views/base.py
webspace/bakery/views/detail.py
webspace/bakery/views/wagtail.py
webspace/cms/__init__.py
webspace/cms/apps.py
webspace/cms/celery.py
webspace/cms/celeryconfig.py
webspace/cms/constants.py
webspace/cms/models.py
webspace/cms/wagtail_hooks.py
webspace/cms/amp/__init__.py
webspace/cms/amp/context_processors.py
webspace/cms/amp/mixins.py
webspace/cms/amp/urls.py
webspace/cms/amp/utils.py
webspace/cms/amp/views.py
webspace/cms/bakery/__init__.py
webspace/cms/bakery/abstract.py
webspace/cms/bakery/apps.py
webspace/cms/bakery/models.py
webspace/cms/templates/build/blocks/grid-info/index-amp.html
webspace/cms/templates/build/blocks/grid-info/index-mobile-amp.html
webspace/cms/templates/build/blocks/grid-info/index-mobile.html
webspace/cms/templates/build/blocks/grid-info/index.html
webspace/cms/templates/build/localhost/blocks/grid-info/index-amp.html
webspace/cms/templates/build/localhost/blocks/grid-info/index-mobile-amp.html
webspace/cms/templates/build/localhost/blocks/grid-info/index-mobile.html
webspace/cms/templates/build/localhost/blocks/grid-info/index.html
webspace-2.7.132.dist-info/LICENSE
webspace-2.7.132.dist-info/METADATA
webspace-2.7.132.dist-info/WHEEL
webspace-2.7.132.dist-info/top_level.txt
webspace-2.7.132.dist-info/RECORD
